uzless_decorator/__init__.py
uzless_decorator/decorators.py
uzless_decorator-0.0.1a0.dist-info/WHEEL
uzless_decorator-0.0.1a0.dist-info/METADATA
uzless_decorator-0.0.1a0.dist-info/RECORD
