Metadata-Version: 2.1
Name: uzless-decorator
Version: 0.0.1a0
Summary: this project aim to simplify architecture description using decorators
Author: Tigran Tchougourian
Author-email: nargitinthenight@gmail.com
Requires-Python: >=3.6,<4.0
Classifier: Programming Language :: Python :: 3
Classifier: Programming Language :: Python :: 3.6
Classifier: Programming Language :: Python :: 3.7
